NBprocessing/__init__.py
NBprocessing/categorical/_NBcategorical_class.py
NBprocessing/categorical/__init__.py
NBprocessing/categorical/_general_functions_categorical.py
NBprocessing/categorical/_input_check_categorical.py
NBprocessing/continuous/_NBcontinuous_class.py
NBprocessing/continuous/__init__.py
NBprocessing/continuous/_input_check_continuous.py
NBprocessing/general/_NBgeneral_class.py
NBprocessing/general/__init__.py
NBprocessing/general/_input_check_general.py
NBprocessing/plot/_NBplot_class.py
NBprocessing/plot/__init__.py
NBprocessing/plot/_input_check_plot.py
NBprocessing/src/__init__.py
NBprocessing/src/_check_input.py
NBprocessing/src/_constance_class.py
NBprocessing/src/_constance_dict.py
NBprocessing-1.1.dist-info/LICENSE
NBprocessing-1.1.dist-info/METADATA
NBprocessing-1.1.dist-info/WHEEL
NBprocessing-1.1.dist-info/top_level.txt
NBprocessing-1.1.dist-info/RECORD
