Metadata-Version: 2.1
Name: NBprocessing
Version: 1.1
Summary: Pre-processing database using pre-written functions
Home-page: https://github.com/nirbarazida/NBprocessing
Author: Nir Barazida
License: UNKNOWN
Platform: UNKNOWN
Classifier: Programming Language :: Python :: 3
Classifier: License :: OSI Approved :: MIT License
Classifier: Operating System :: OS Independent
Requires-Dist: pandas
Requires-Dist: numpy
Requires-Dist: matplotlib
Requires-Dist: seaborn
Requires-Dist: plotly
Requires-Dist: scikit-learn
